{
  "id": "c28432e0-ed46-4dac-9f1b-092cae99c20e",
  "prevId": "00000000-0000-0000-0000-000000000000",
  "version": "7",
  "dialect": "postgresql",
  "tables": {
    "public.field_updates": {
      "name": "field_updates",
      "schema": "",
      "columns": {
        "id": {
          "name": "id",
          "type": "integer",
          "primaryKey": true,
          "notNull": true,
          "identity": {
            "type": "always",
            "name": "field_updates_id_seq",
            "schema": "public",
            "increment": "1",
            "startWith": "1",
            "minValue": "1",
            "maxValue": "2147483647",
            "cache": "1",
            "cycle": false
          }
        },
        "field_id": {
          "name": "field_id",
          "type": "integer",
          "primaryKey": false,
          "notNull": true
        },
        "agent_id": {
          "name": "agent_id",
          "type": "integer",
          "primaryKey": false,
          "notNull": true
        },
        "stage": {
          "name": "stage",
          "type": "field_stage",
          "typeSchema": "public",
          "primaryKey": false,
          "notNull": true
        },
        "notes": {
          "name": "notes",
          "type": "text",
          "primaryKey": false,
          "notNull": false
        },
        "created_at": {
          "name": "created_at",
          "type": "timestamp",
          "primaryKey": false,
          "notNull": true,
          "default": "now()"
        }
      },
      "indexes": {},
      "foreignKeys": {
        "field_updates_field_id_fields_id_fk": {
          "name": "field_updates_field_id_fields_id_fk",
          "tableFrom": "field_updates",
          "tableTo": "fields",
          "columnsFrom": [
            "field_id"
          ],
          "columnsTo": [
            "id"
          ],
          "onDelete": "cascade",
          "onUpdate": "no action"
        },
        "field_updates_agent_id_users_id_fk": {
          "name": "field_updates_agent_id_users_id_fk",
          "tableFrom": "field_updates",
          "tableTo": "users",
          "columnsFrom": [
            "agent_id"
          ],
          "columnsTo": [
            "id"
          ],
          "onDelete": "no action",
          "onUpdate": "no action"
        }
      },
      "compositePrimaryKeys": {},
      "uniqueConstraints": {},
      "policies": {},
      "checkConstraints": {},
      "isRLSEnabled": false
    },
    "public.fields": {
      "name": "fields",
      "schema": "",
      "columns": {
        "id": {
          "name": "id",
          "type": "integer",
          "primaryKey": true,
          "notNull": true,
          "identity": {
            "type": "always",
            "name": "fields_id_seq",
            "schema": "public",
            "increment": "1",
            "startWith": "1",
            "minValue": "1",
            "maxValue": "2147483647",
            "cache": "1",
            "cycle": false
          }
        },
        "name": {
          "name": "name",
          "type": "varchar(150)",
          "primaryKey": false,
          "notNull": true
        },
        "crop_type": {
          "name": "crop_type",
          "type": "varchar(100)",
          "primaryKey": false,
          "notNull": true
        },
        "location": {
          "name": "location",
          "type": "varchar(255)",
          "primaryKey": false,
          "notNull": false
        },
        "planting_date": {
          "name": "planting_date",
          "type": "timestamp",
          "primaryKey": false,
          "notNull": true
        },
        "expected_harvest_date": {
          "name": "expected_harvest_date",
          "type": "timestamp",
          "primaryKey": false,
          "notNull": false
        },
        "current_stage": {
          "name": "current_stage",
          "type": "field_stage",
          "typeSchema": "public",
          "primaryKey": false,
          "notNull": true,
          "default": "'planted'"
        },
        "assigned_agent_id": {
          "name": "assigned_agent_id",
          "type": "integer",
          "primaryKey": false,
          "notNull": false
        },
        "created_at": {
          "name": "created_at",
          "type": "timestamp",
          "primaryKey": false,
          "notNull": true,
          "default": "now()"
        },
        "updated_at": {
          "name": "updated_at",
          "type": "timestamp",
          "primaryKey": false,
          "notNull": true,
          "default": "now()"
        }
      },
      "indexes": {},
      "foreignKeys": {
        "fields_assigned_agent_id_users_id_fk": {
          "name": "fields_assigned_agent_id_users_id_fk",
          "tableFrom": "fields",
          "tableTo": "users",
          "columnsFrom": [
            "assigned_agent_id"
          ],
          "columnsTo": [
            "id"
          ],
          "onDelete": "set null",
          "onUpdate": "no action"
        }
      },
      "compositePrimaryKeys": {},
      "uniqueConstraints": {},
      "policies": {},
      "checkConstraints": {},
      "isRLSEnabled": false
    },
    "public.users": {
      "name": "users",
      "schema": "",
      "columns": {
        "id": {
          "name": "id",
          "type": "integer",
          "primaryKey": true,
          "notNull": true,
          "identity": {
            "type": "always",
            "name": "users_id_seq",
            "schema": "public",
            "increment": "1",
            "startWith": "1",
            "minValue": "1",
            "maxValue": "2147483647",
            "cache": "1",
            "cycle": false
          }
        },
        "full_name": {
          "name": "full_name",
          "type": "varchar(150)",
          "primaryKey": false,
          "notNull": true
        },
        "email": {
          "name": "email",
          "type": "varchar(100)",
          "primaryKey": false,
          "notNull": true
        },
        "password": {
          "name": "password",
          "type": "text",
          "primaryKey": false,
          "notNull": true
        },
        "role": {
          "name": "role",
          "type": "user_role",
          "typeSchema": "public",
          "primaryKey": false,
          "notNull": true,
          "default": "'field_agent'"
        },
        "created_at": {
          "name": "created_at",
          "type": "timestamp",
          "primaryKey": false,
          "notNull": true,
          "default": "now()"
        }
      },
      "indexes": {},
      "foreignKeys": {},
      "compositePrimaryKeys": {},
      "uniqueConstraints": {
        "users_email_unique": {
          "name": "users_email_unique",
          "nullsNotDistinct": false,
          "columns": [
            "email"
          ]
        }
      },
      "policies": {},
      "checkConstraints": {},
      "isRLSEnabled": false
    }
  },
  "enums": {
    "public.field_stage": {
      "name": "field_stage",
      "schema": "public",
      "values": [
        "planted",
        "growing",
        "ready",
        "harvested"
      ]
    },
    "public.user_role": {
      "name": "user_role",
      "schema": "public",
      "values": [
        "admin",
        "field_agent"
      ]
    }
  },
  "schemas": {},
  "sequences": {},
  "roles": {},
  "policies": {},
  "views": {},
  "_meta": {
    "columns": {},
    "schemas": {},
    "tables": {}
  }
}